seqoptools/__init__.py
seqoptools-0.0.1.dist-info/METADATA
seqoptools-0.0.1.dist-info/WHEEL
seqoptools-0.0.1.dist-info/licenses/LICENSE
seqoptools-0.0.1.dist-info/RECORD
