Metadata-Version: 2.3
Name: seqoptools
Version: 0.0.1
Summary: Efficients tools to deal with differents kinds of sequences.
Project-URL: Homepage, https://github.com/Darix001/seqtools.git
Project-URL: Issues, https://github.com/Darix001/seqtools/seqtools
Author-email: Dariel Enmanuel Buret Rivera <darielburetrivera@gmail.com>
License-File: LICENSE
Classifier: License :: OSI Approved :: MIT License
Classifier: Operating System :: OS Independent
Classifier: Programming Language :: Python :: 3
Requires-Python: >=3.12
